napari_molecule_reader/__init__.py
napari_molecule_reader/_reader.py
napari_molecule_reader/_version.py
napari_molecule_reader/bonds.py
napari_molecule_reader/colors.py
napari_molecule_reader/molecule_reader.py
napari_molecule_reader/napari.yaml
napari_molecule_reader/_tests/__init__.py
napari_molecule_reader/_tests/test_reader.py
napari_molecule_reader-0.1.4.dist-info/licenses/LICENSE
napari_molecule_reader-0.1.4.dist-info/METADATA
napari_molecule_reader-0.1.4.dist-info/WHEEL
napari_molecule_reader-0.1.4.dist-info/entry_points.txt
napari_molecule_reader-0.1.4.dist-info/top_level.txt
napari_molecule_reader-0.1.4.dist-info/RECORD
