Metadata-Version: 2.4
Name: napari-molecule-reader
Version: 0.1.4
Summary: A napari plugin that read molecular structure files.
Author: Lorenzo Gaifas
Author-email: brisvag@gmail.com
License: 
Project-URL: Bug Tracker, https://github.com/brisvag/napari-molecule-reader/issues
Project-URL: Documentation, https://github.com/brisvag/napari-molecule-reader#README.md
Project-URL: Source Code, https://github.com/brisvag/napari-molecule-reader
Project-URL: User Support, https://github.com/brisvag/napari-molecule-reader/issues
Classifier: Development Status :: 2 - Pre-Alpha
Classifier: Framework :: napari
Classifier: Intended Audience :: Developers
Classifier: License :: OSI Approved :: GNU General Public License v3 (GPLv3)
Classifier: Operating System :: OS Independent
Classifier: Programming Language :: Python
Classifier: Programming Language :: Python :: 3
Classifier: Programming Language :: Python :: 3 :: Only
Classifier: Programming Language :: Python :: 3.10
Classifier: Programming Language :: Python :: 3.11
Classifier: Programming Language :: Python :: 3.12
Classifier: Programming Language :: Python :: 3.13
Classifier: Topic :: Scientific/Engineering :: Image Processing
Requires-Python: >=3.10
License-File: LICENSE
Requires-Dist: atomium
Requires-Dist: numpy
Requires-Dist: pandas
Requires-Dist: scipy
Provides-Extra: testing
Requires-Dist: tox; extra == "testing"
Requires-Dist: pytest; extra == "testing"
Requires-Dist: pytest-cov; extra == "testing"
Dynamic: license-file
